setup.py
src/pyesl/__init__.py
src/pyesl/aggs.py
src/pyesl/client.py
src/pyesl/conf.py
src/pyesl/errors.py
src/pyesl/field.py
src/pyesl/query.py
src/pyesl/response.py
src/pyesl/search.py
src/pyesl.egg-info/PKG-INFO
src/pyesl.egg-info/SOURCES.txt
src/pyesl.egg-info/dependency_links.txt
src/pyesl.egg-info/requires.txt
src/pyesl.egg-info/top_level.txt
src/pyesl/parser/__init__.py
src/pyesl/parser/query.py
src/pyesl/parser/response.py