Metadata-Version: 1.1
Name: pyesl
Version: 0.2.2.dev0
Summary: A flexible high level library for python elasticsearch development that inherited and learned form elasticsearch-dsl.
Home-page: UNKNOWN
Author: pyesl team
Author-email: dennias.chiu@gmail.com
License: BSD
Platform: UNKNOWN
Classifier: Development Status :: 5 - Production/Stable
Classifier: Environment :: Web Environment
Classifier: Intended Audience :: Developers
Classifier: License :: OSI Approved :: BSD License
Classifier: Operating System :: OS Independent
Classifier: Programming Language :: Python :: 3
Classifier: Programming Language :: Python :: 3.7
Classifier: Topic :: Internet :: WWW/HTTP :: Dynamic Content
Classifier: Topic :: Software Development :: Libraries :: Python Modules
